{
  "i18n_apex":					"mycomosi-wc-apex",
  "i18n_about":                   "About",
  "i18n_help":                    "Help",
  "i18n_topo":					"Topology Analyzer",
  "i18n_apex_text":				"Topology Analyzer Custom Element",
  "i18n_required_objs":			"Graph missing required Objects",
  "i18n_empty_elements":          "Vertices[] must contain elements",
  "i18n_vertices_required_objs":	"Vertices - some required Objects are missing",
  "i18n_edges_required_objs":		"Edges - some required Objects are missing",
  "i18n_discovery_failed" : 		"Error while discovering neighbours",
  "i18n_apex_menu_neighbours" : 	"Discover neighbours",
  "i18n_alert_manager":           "Alert Manager",
  "i18n_panel_loading":           "Loading...",
  "i18n_circuit_name":            "Circuit Name",
  "i18n_unexpected_error":        "Unexpected Error",
  "i18n_unexpected_error_msg":    "An unexpected error occurred",

  "i18n_viewport_names":          "Loading Topology Viewport...",
  "i18n_loading_alert_list":      "Loading alert list...",
  "i18n_model_instance_names":    "Related Circuits",
  "i18n_mo_property_names":       "MO Properties",

  "i18n_id":                      "Id",
  "i18n_name":                    "Name",
  "i18n_class":                   "Class",
  "i18n_customer":                "Customer",
  "i18n_manage_icons":            "Manage Icons",
  "i18n_administration":          "Administration",
  "i18n_log_out":                 "Log Out",
  "i18n_filter_no_results":       "Filter Has No Results",
  "i18n_relationship":            "Relationship",
  "i18n_select_a_relationship":   "Select a relationship",
  "i18n_select_a_class":          "Select a manager class",
  "i18n_applying_configuration":  "Applying configuration...",
  "i18n_apply":                   "Apply",

  "i18n_affected_entities":       "Affected Entities",
  "i18n_root_cause_entities":     "Root Cause Entities",
  "i18n_loading_problems":        "Loading problems list...",
  "i18n_entity_type":             "Entity Type",
  "i18n_node_type":               "Node Type",
  "i18n_node_instance":           "Node Instance",
  "i18n_state":                   "State",
  "i18n_request_failed":          "Request Failed",
  "i18n_ok":                      "OK",

  "i18n_global_settings":         "Global Settings",
  "i18n_timeouts_and_settings":   "Timeouts and Settings",
  "i18n_label_truncation":        "Label Truncation",
  "i18n_cntnmnt_relationship":    "Containment Relationship",
  "i18n_icon_management":         "Icon Management",
  "i18n_menu_items":              "Menu Items",
  "i18n_theme":                   "Theme",
  "i18n_language":                "Language",
  "i18n_nx":                      "NX",

  "i18n_save":                    "Save",
  "i18n_reset":                   "Reset",
  "i18n_close":                   "Close",
  "i18n_delete":                  "Delete",

  "i18n_show":                    "Show",
  "i18n_start":                   "Start",
  "i18n_end":                     "End",
  "i18n_Saved_truncation_rules":  "Saved Truncation Rules",
  "i18n_applied_to":              "Applied to",
  "i18n_show_at":                 "Show at",
  "i18n_topology_elements":       "topology elements",
  "i18n_classes":                 "classes",
  "i18n_create_new_truncation":   "Create new truncation rule",
  "i18n_no":                      "No",
  "i18n_ellipsis_characters":     "Ellipsis Character(s)",
  "i18n_truncate_to":             "Truncate to",
  "i18n_endpoints":               "Endpoints",
  "i18n_edges":                   "Edges",
  "i18n_nodes":                   "Nodes",
  "i18n_create":                  "Create",
  "i18n_cancel":                  "Cancel",

  "i18n_missing_dropzone":        "Missing required module dropzone.js",
  "i18n_click_here":              "Click here",
  "i18n_or":                      "or",
  "i18n_dd_containment_here":     "drag/drop containment relationship configuration file here",
  "i18n_must_be_csv":             "Must be .csv extension",
  "i18n_export":                  "Export",
  "i18n_exporting":               "Exporting",
  "i18n_file_error":              "File Error",
  "i18n_edit":                    "edit",
  "i18n_upload":                  "upload",
  "i18n_files":                   "files",
  "i18n_dragdrophere":            "drag/drop icon files here",
  "i18n_available_icons":         "Available Icons",
  "i18n_set_as_default_icon":     "Set as default icon",
  "i18n_filters":                 "filters",
  "i18n_attribute":               "Attribute",
  "i18n_value":                   "Value",
  "i18n_sign_out":                "Sign Out"
}
